models/cache.py
models/llama_config.py
models/modeling_llama2.py
models/modeling_llama3_1.py
models/modeling_qwen2_5.py
models/qwen2_5_config.py
models/tp.py
utils/decoding.py
utils/graph_infer.py
utils/medusa_choices.py
utils/medusa_utils.py
utils/misc.py
utils/n_gram.py
utils/sampling.py
tokenswift-0.1.1.dist-info/LICENSE
tokenswift-0.1.1.dist-info/METADATA
tokenswift-0.1.1.dist-info/WHEEL
tokenswift-0.1.1.dist-info/top_level.txt
tokenswift-0.1.1.dist-info/RECORD
