Metadata-Version: 2.2
Name: tokenswift
Version: 0.1.1
Summary: Framework for Accelerating LLM Generation
Classifier: Programming Language :: Python :: 3
Classifier: License :: OSI Approved :: Apache Software License
Requires-Python: >=3.11
License-File: LICENSE
Requires-Dist: accelerate==1.0.1
Requires-Dist: datasets==3.0.1
Requires-Dist: einops==0.8.0
Requires-Dist: matplotlib==3.10.0
Requires-Dist: protobuf==5.28.2
Requires-Dist: sentencepiece==0.2.0
Requires-Dist: termcolor==2.5.0
Requires-Dist: tiktoken==0.6.0
Requires-Dist: tokenizers==0.21.0
Requires-Dist: torch==2.4.0
Requires-Dist: tqdm==4.66.5
Requires-Dist: transformers==4.47.1
Requires-Dist: triton==3.0.0
Requires-Dist: sortedcontainers
Requires-Dist: tensorboard
